clang_tools/__init__.py
clang_tools/install.py
clang_tools/main.py
clang_tools/util.py
clang_tools-0.15.3.dist-info/licenses/LICENSE
clang_tools-0.15.3.dist-info/METADATA
clang_tools-0.15.3.dist-info/WHEEL
clang_tools-0.15.3.dist-info/entry_points.txt
clang_tools-0.15.3.dist-info/top_level.txt
clang_tools-0.15.3.dist-info/RECORD
