Metadata-Version: 2.4
Name: clang_tools
Version: 0.15.3
Summary: Install clang-tools (clang-format, clang-tidy, clang-query, clang-apply-replacements) with pip
Author-email: Xianpeng Shen <xianpeng.shen@gmail.com>, Brendan Doherty <2bndy5@gmail.com>
License-Expression: MIT
Project-URL: source, https://github.com/cpp-linter/clang-tools-pip
Project-URL: tracker, https://github.com/cpp-linter/clang-tools-pip/issues
Keywords: clang,clang-tools,clang-extra,clang-tidy,clang-format,clang-query,clang-apply-replacements
Classifier: Development Status :: 5 - Production/Stable
Classifier: Intended Audience :: Developers
Classifier: Intended Audience :: System Administrators
Classifier: Intended Audience :: Information Technology
Classifier: Natural Language :: English
Classifier: Operating System :: Microsoft :: Windows
Classifier: Operating System :: POSIX :: Linux
Classifier: Operating System :: MacOS
Classifier: Programming Language :: Python :: 3.9
Classifier: Programming Language :: Python :: 3.10
Classifier: Programming Language :: Python :: 3.11
Classifier: Programming Language :: Python :: 3.12
Classifier: Programming Language :: Python :: 3.13
Classifier: Topic :: Software Development :: Build Tools
License-File: LICENSE
Provides-Extra: dev
Requires-Dist: coverage[toml]; extra == "dev"
Requires-Dist: pre-commit; extra == "dev"
Requires-Dist: pytest; extra == "dev"
Provides-Extra: docs
Requires-Dist: sphinx; extra == "docs"
Requires-Dist: sphinx-autobuild; extra == "docs"
Requires-Dist: sphinx_immaterial; extra == "docs"
Dynamic: license-file
